README.rst
setup.py
dynamodb_beaker/__init__.py
dynamodb_beaker.egg-info/PKG-INFO
dynamodb_beaker.egg-info/SOURCES.txt
dynamodb_beaker.egg-info/dependency_links.txt
dynamodb_beaker.egg-info/entry_points.txt
dynamodb_beaker.egg-info/requires.txt
dynamodb_beaker.egg-info/top_level.txt