Metadata-Version: 1.1
Name: dynamodb-beaker
Version: 0.1.1
Summary: DynamoDB backend for Beaker
Home-page: https://github.com/xica/dynamodb-beaker
Author: xica development team
Author-email: info@xica.net
License: MIT
Platform: UNKNOWN
Classifier: Development Status :: 3 - Alpha
Classifier: Environment :: Web Environment
Classifier: Framework :: Pyramid
Classifier: Intended Audience :: Developers
Classifier: License :: OSI Approved :: MIT License
Classifier: Operating System :: POSIX :: Linux
Classifier: Programming Language :: Python
Classifier: Topic :: Database
